{"generated":"2021-06-22T13:37:29.335064282Z","published":"2020-06-04T07:39:42Z","app":"watchexec","version":"1.13.0","notes":"<ul>\n<li><a class=\"issue-link js-issue-link\" data-error-text=\"Failed to load title\" data-id=\"576850129\" data-permission-text=\"Title is private\" data-url=\"https://github.com/watchexec/watchexec/issues/147\" data-hovercard-type=\"pull_request\" data-hovercard-url=\"/watchexec/watchexec/pull/147/hovercard\" href=\"https://github.com/watchexec/watchexec/pull/147\">#147</a>: .gitignore files are now looked at in children <em>as well as parents</em>, the latter being very much not what should happen, but I'm kinda stuck with it at the moment to avoid breaking behaviour, eeech</li>\n<li><a class=\"issue-link js-issue-link\" data-error-text=\"Failed to load title\" data-id=\"601971215\" data-permission-text=\"Title is private\" data-url=\"https://github.com/watchexec/watchexec/issues/150\" data-hovercard-type=\"pull_request\" data-hovercard-url=\"/watchexec/watchexec/pull/150/hovercard\" href=\"https://github.com/watchexec/watchexec/pull/150\">#150</a>: clarity around time units in the interface</li>\n<li>Deps: <code>notify</code> (patch), <code>globset</code> (patch), <code>clap</code> (patch), <code>nix</code> (major: 0.15 → 0.17)</li>\n</ul>","downloads":[{"url":"https://github.com/watchexec/watchexec/releases/download/1.13.0/watchexec-1.13.0-i686-unknown-linux-musl.tar.xz","filename":"watchexec-1.13.0-i686-unknown-linux-musl.tar.xz","size":647200,"format":{"short":"XZ","long":"Xzipped tarball","tool":"tar xJf"},"sums":[],"cats":["Linux","x86","musl"]},{"url":"https://github.com/watchexec/watchexec/releases/download/1.13.0/watchexec-1.13.0-x86_64-unknown-linux-gnu.deb","filename":"watchexec-1.13.0-x86_64-unknown-linux-gnu.deb","size":639410,"format":{"short":"DEB","long":"Debian/Ubuntu package","tool":"dpkg -i"},"sums":[],"cats":["Linux","x86-64","glibc"]},{"url":"https://github.com/watchexec/watchexec/releases/download/1.13.0/watchexec-1.13.0-x86_64-unknown-linux-gnu.tar.xz","filename":"watchexec-1.13.0-x86_64-unknown-linux-gnu.tar.xz","size":643616,"format":{"short":"XZ","long":"Xzipped tarball","tool":"tar xJf"},"sums":[],"cats":["Linux","x86-64","glibc"]},{"url":"https://github.com/watchexec/watchexec/releases/download/1.13.0/watchexec-1.13.0-x86_64-unknown-linux-musl.tar.xz","filename":"watchexec-1.13.0-x86_64-unknown-linux-musl.tar.xz","size":659716,"format":{"short":"XZ","long":"Xzipped tarball","tool":"tar xJf"},"sums":[],"cats":["Linux","x86-64","musl"]},{"url":"https://github.com/watchexec/watchexec/releases/download/1.13.0/watchexec-1.13.0-x86_64-pc-windows-msvc.zip","filename":"watchexec-1.13.0-x86_64-pc-windows-msvc.zip","size":772680,"format":{"short":"Zip","long":"Zipped folder","tool":"unzip"},"sums":[],"cats":["Windows","x86-64","MSVC"]},{"url":"https://github.com/watchexec/watchexec/releases/download/1.13.0/watchexec-1.13.0-x86_64-pc-windows-gnu.zip","filename":"watchexec-1.13.0-x86_64-pc-windows-gnu.zip","size":813962,"format":{"short":"Zip","long":"Zipped folder","tool":"unzip"},"sums":[],"cats":["Windows","x86-64","MingW"]},{"url":"https://github.com/watchexec/watchexec/releases/download/1.13.0/watchexec-1.13.0-x86_64-apple-darwin.tar.xz","filename":"watchexec-1.13.0-x86_64-apple-darwin.tar.xz","size":589536,"format":{"short":"XZ","long":"Xzipped tarball","tool":"tar xJf"},"sums":[],"cats":["macOS","x86-64",null]}],"sums":[]}