{"generated":"2021-06-22T13:40:25.427140286Z","published":"2018-09-09T03:03:55Z","app":"watchexec","version":"1.9.1","notes":"<ul>\n<li><a class=\"issue-link js-issue-link\" data-error-text=\"Failed to load title\" data-id=\"281977645\" data-permission-text=\"Title is private\" data-url=\"https://github.com/watchexec/watchexec/issues/74\" data-hovercard-type=\"pull_request\" data-hovercard-url=\"/watchexec/watchexec/pull/74/hovercard\" href=\"https://github.com/watchexec/watchexec/pull/74\">#74</a> — Watchexec no longer panics on missing folders — patch<sup><strong>1, 2</strong></sup></li>\n<li><a class=\"issue-link js-issue-link\" data-error-text=\"Failed to load title\" data-id=\"352699054\" data-permission-text=\"Title is private\" data-url=\"https://github.com/watchexec/watchexec/issues/95\" data-hovercard-type=\"pull_request\" data-hovercard-url=\"/watchexec/watchexec/pull/95/hovercard\" href=\"https://github.com/watchexec/watchexec/pull/95\">#95</a> — Fix issues with whitespace in commands — patch<sup><strong>2</strong></sup></li>\n<li><a class=\"issue-link js-issue-link\" data-error-text=\"Failed to load title\" data-id=\"356592084\" data-permission-text=\"Title is private\" data-url=\"https://github.com/watchexec/watchexec/issues/96\" data-hovercard-type=\"pull_request\" data-hovercard-url=\"/watchexec/watchexec/pull/96/hovercard\" href=\"https://github.com/watchexec/watchexec/pull/96\">#96</a> — Add install instructions for Arch Linux — docs</li>\n<li>Create a Debian package on release — releng</li>\n<li>Add install instructions for Debian — docs</li>\n</ul>\n<p><sub> <strong>1:</strong> Other changes were added following this to convert more panics into normal errors: some glob parsing errors, and file watcher initialisation errors.</sub></p>\n<p><sub> <strong>2:</strong> These changes also cause a breaking changes to the library interface, but this is not considered in the version numbers (i.e. if you use it, <em>pin it</em>). From cursory investigation only <a href=\"https://github.com/passcod/cargo-watch\">cargo-watch</a> is a consumer and changes there in consequence are coordinated.</sub></p>","downloads":[{"url":"https://github.com/watchexec/watchexec/releases/download/1.9.1/watchexec-1.9.1-i686-unknown-linux-musl.tar.gz","filename":"watchexec-1.9.1-i686-unknown-linux-musl.tar.gz","size":1835752,"format":{"short":"GZ","long":"Gzipped tarball","tool":"tar xzf"},"sums":[],"cats":["Linux","x86","musl"]},{"url":"https://github.com/watchexec/watchexec/releases/download/1.9.1/watchexec-1.9.1-x86_64-unknown-linux-gnu.deb","filename":"watchexec-1.9.1-x86_64-unknown-linux-gnu.deb","size":1125720,"format":{"short":"DEB","long":"Debian/Ubuntu package","tool":"dpkg -i"},"sums":[],"cats":["Linux","x86-64","glibc"]},{"url":"https://github.com/watchexec/watchexec/releases/download/1.9.1/watchexec-1.9.1-x86_64-unknown-linux-gnu.tar.gz","filename":"watchexec-1.9.1-x86_64-unknown-linux-gnu.tar.gz","size":1512004,"format":{"short":"GZ","long":"Gzipped tarball","tool":"tar xzf"},"sums":[],"cats":["Linux","x86-64","glibc"]},{"url":"https://github.com/watchexec/watchexec/releases/download/1.9.1/watchexec-1.9.1-x86_64-unknown-linux-musl.tar.gz","filename":"watchexec-1.9.1-x86_64-unknown-linux-musl.tar.gz","size":1909449,"format":{"short":"GZ","long":"Gzipped tarball","tool":"tar xzf"},"sums":[],"cats":["Linux","x86-64","musl"]},{"url":"https://github.com/watchexec/watchexec/releases/download/1.9.1/watchexec-1.9.1-x86_64-apple-darwin.tar.gz","filename":"watchexec-1.9.1-x86_64-apple-darwin.tar.gz","size":926116,"format":{"short":"GZ","long":"Gzipped tarball","tool":"tar xzf"},"sums":[],"cats":["macOS","x86-64",null]}],"sums":[]}